hodl_cli/__init__.py
hodl_cli/app.py
hodl_cli/cli.py
hodl_cli-2.0.1.dist-info/entry_points.txt
hodl_cli-2.0.1.dist-info/LICENSE
hodl_cli-2.0.1.dist-info/WHEEL
hodl_cli-2.0.1.dist-info/METADATA
hodl_cli-2.0.1.dist-info/RECORD
