Metadata-Version: 2.1
Name: hodl-cli
Version: 2.0.1
Summary: Dollar-cost averaging for crypto on the command line.
License: MIT
Author: Mark Hudnall
Author-email: me@markhudnall.com
Requires-Python: >=3.8,<4.0
Classifier: Development Status :: 5 - Production/Stable
Classifier: Environment :: Console
Classifier: Intended Audience :: Developers
Classifier: Intended Audience :: End Users/Desktop
Classifier: Intended Audience :: Financial and Insurance Industry
Classifier: Intended Audience :: Information Technology
Classifier: License :: OSI Approved :: MIT License
Classifier: Operating System :: OS Independent
Classifier: Programming Language :: Python :: 3
Classifier: Programming Language :: Python :: 3.8
Classifier: Programming Language :: Python :: 3.9
Classifier: Topic :: Office/Business :: Financial
Classifier: Topic :: Office/Business :: Financial :: Investment
Classifier: Topic :: Security :: Cryptography
Requires-Dist: cbpro (>=1.1.4,<2.0.0)
Requires-Dist: click (>=7.1.2,<8.0.0)
Requires-Dist: python-dateutil (>=2.8.1,<3.0.0)
Requires-Dist: requests (>=2.13.0,<3.0.0)
